myminions/__init__.py
myminions/minions.py
myminions/testing.py
tests/__init__.py
tests/test_pyyaml.py
tests/resources/resources_index.md
tests/resources/sample-1/.hidden
tests/resources/sample-1/file-1.txt
tests/resources/sample-1/file-2.csv
myminions-0.4.0.dist-info/METADATA
myminions-0.4.0.dist-info/WHEEL
myminions-0.4.0.dist-info/top_level.txt
myminions-0.4.0.dist-info/RECORD
