Metadata-Version: 2.1
Name: myminions
Version: 0.4.0
Summary: Loose collection of methods doing basic bidding's.
Home-page: https://https://gitlab.com/david.scheliga/myminions
Author: David Scheliga
License: GNU General Public License V3 (GPLv3)
Project-URL: Documentation, https://myminions.readthedocs.io/en/latest/
Project-URL: Source Code Repository, https://gitlab.com/david.scheliga/myminions
Keywords: helper,filesystem,walk
Platform: UNKNOWN
Classifier: Development Status :: 5 - Production/Stable
Classifier: License :: OSI Approved :: GNU General Public License v3 (GPLv3)
Classifier: Operating System :: OS Independent
Classifier: Programming Language :: Python :: 3
Classifier: Programming Language :: Python :: 3.6
Classifier: Programming Language :: Python :: 3.7
Classifier: Programming Language :: Python :: 3.8
Classifier: Programming Language :: Python :: 3.9
Requires-Python: >=3.6
Requires-Dist: pyyaml
Requires-Dist: pathwalker
